{
  "reward": {
    "get_mag": 0,
    "dvl_before": [
      {
        "agi": 49,
        "exceed_info": {
          "opened_num": 0
        },
        "hpmx": 448,
        "luk": 57,
        "devicon_power": 1036,
        "hp": 448,
        "recommend_type": 0,
        "lv": 27,
        "additional_skl": [],
        "mdef": 275,
        "limitbreak": {
          "effect": [],
          "num": 60,
          "open": []
        },
        "is_awk": false,
        "dr": 0,
        "ai_auto_type": 0,
        "mag": 32,
        "limitbreak_skl": [],
        "arc": 0,
        "wk": 4,
        "skl": [
          {
            "lv": 1,
            "id": 3028
          },
          {
            "lv": 1,
            "id": 1176
          },
          {
            "lv": 1,
            "id": 1019
          },
          {
            "lv": 1,
            "id": 103015
          },
          {
            "lv": 0,
            "id": 0
          },
          {
            "lv": 0,
            "id": 0
          }
        ],
        "id": 11750,
        "patk": 362,
        "exp": 16938,
        "vit": 53,
        "is_released_learn_only_skill": false,
        "st": 0,
        "pdef": 298,
        "mp": 10,
        "mgtm_effs": [],
        "mgtms": [],
        "str": 77,
        "av": 8,
        "spt": 0,
        "uniq": 30478222781,
        "matk": 268,
        "mpmx": 10,
        "rp": 0,
        "rarity": 3,
        "contents_type": 0
      }
    ],
    "item": [
      {
        "num": 1,
        "is_bonus": false,
        "id": 7100,
        "type": 2
      },
      {
        "param": "5013",
        "num": 8,
        "is_bonus": false,
        "id": 1100013,
        "type": 14
      },
      {
        "mgtm": {
          "prc": 300,
          "effs": [
            {
              "val": 1,
              "type": 15
            },
            {
              "val": 2,
              "type": 1
            },
            {
              "val": 2,
              "type": 6
            }
          ],
          "nxt_mval": 2,
          "nxt_mval_9": 9,
          "part": 5,
          "nxt_sval_max": 2,
          "lv": 1,
          "nxt_sval": 3,
          "uniq": 30385715128,
          "nxt_mval_max": 9,
          "nxt_sval_9": 2,
          "is_lock": false,
          "id": 508
        },
        "num": 1,
        "is_bonus": false,
        "id": 508,
        "type": 6
      }
    ],
    "usr_lv": {
      "exp_pre": 59681,
      "level": 27,
      "exp_next": [
        56290,
        63387
      ],
      "id": 225973463,
      "exp_new": 60851
    },
    "smn_lv": [],
    "curr_mag": 0,
    "dbl_exp_plus": 731,
    "usr_exp_plus": 1170,
    "magatama_rate": 1,
    "get_money": 909,
    "smn": [
      {
        "skl_p": 19,
        "level": 15,
        "next_lv_exp": 1907,
        "skl": [
          25010
        ],
        "exists_chara_quest": true,
        "uniq": 30205482102,
        "is_awaken": false,
        "lineup": [
          {
            "exist_up_skill": false,
            "is_support": true,
            "is_awaken": false,
            "is_lock": false,
            "need_point": 1,
            "id": 100060,
            "is_learned": false
          },
          {
            "exist_up_skill": true,
            "is_support": false,
            "is_awaken": false,
            "is_lock": false,
            "need_point": 1,
            "id": 10110,
            "is_learned": false
          },
          {
            "exist_up_skill": true,
            "is_support": false,
            "is_awaken": false,
            "is_lock": true,
            "need_point": 3,
            "id": 10120,
            "is_learned": false
          },
          {
            "exist_up_skill": false,
            "is_support": false,
            "is_awaken": false,
            "is_lock": true,
            "need_point": 5,
            "id": 10130,
            "is_learned": false
          },
          {
            "exist_up_skill": true,
            "is_support": false,
            "is_awaken": false,
            "is_lock": false,
            "need_point": 1,
            "id": 10410,
            "is_learned": false
          },
          {
            "exist_up_skill": true,
            "is_support": false,
            "is_awaken": false,
            "is_lock": true,
            "need_point": 3,
            "id": 10420,
            "is_learned": false
          },
          {
            "exist_up_skill": false,
            "is_support": false,
            "is_awaken": false,
            "is_lock": true,
            "need_point": 5,
            "id": 10430,
            "is_learned": false
          },
          {
            "exist_up_skill": true,
            "is_support": false,
            "is_awaken": false,
            "is_lock": false,
            "need_point": 0,
            "id": 25010,
            "is_learned": true
          },
          {
            "exist_up_skill": false,
            "is_support": false,
            "is_awaken": false,
            "is_lock": false,
            "need_point": 10,
            "id": 25020,
            "is_learned": false
          },
          {
            "exist_up_skill": true,
            "is_support": false,
            "is_awaken": false,
            "is_lock": false,
            "need_point": 2,
            "id": 25310,
            "is_learned": false
          },
          {
            "exist_up_skill": true,
            "is_support": false,
            "is_awaken": false,
            "is_lock": true,
            "need_point": 4,
            "id": 25320,
            "is_learned": false
          },
          {
            "exist_up_skill": false,
            "is_support": false,
            "is_awaken": false,
            "is_lock": true,
            "need_point": 6,
            "id": 25330,
            "is_learned": false
          },
          {
            "exist_up_skill": true,
            "is_support": false,
            "is_awaken": false,
            "is_lock": false,
            "need_point": 2,
            "id": 111710,
            "is_learned": false
          },
          {
            "exist_up_skill": true,
            "is_support": false,
            "is_awaken": false,
            "is_lock": true,
            "need_point": 4,
            "id": 111720,
            "is_learned": false
          },
          {
            "exist_up_skill": false,
            "is_support": false,
            "is_awaken": false,
            "is_lock": true,
            "need_point": 6,
            "id": 111730,
            "is_learned": false
          },
          {
            "exist_up_skill": true,
            "is_support": false,
            "is_awaken": false,
            "is_lock": false,
            "need_point": 2,
            "id": 111810,
            "is_learned": false
          },
          {
            "exist_up_skill": true,
            "is_support": false,
            "is_awaken": false,
            "is_lock": true,
            "need_point": 4,
            "id": 111820,
            "is_learned": false
          },
          {
            "exist_up_skill": false,
            "is_support": false,
            "is_awaken": false,
            "is_lock": true,
            "need_point": 6,
            "id": 111830,
            "is_learned": false
          },
          {
            "exist_up_skill": true,
            "is_support": false,
            "is_awaken": true,
            "is_lock": true,
            "need_point": 3,
            "id": 23510,
            "is_learned": false
          },
          {
            "exist_up_skill": false,
            "is_support": false,
            "is_awaken": true,
            "is_lock": true,
            "need_point": 7,
            "id": 23520,
            "is_learned": false
          },
          {
            "exist_up_skill": false,
            "is_support": false,
            "is_awaken": true,
            "is_lock": true,
            "need_point": 10,
            "id": 130310,
            "is_learned": false
          },
          {
            "exist_up_skill": false,
            "is_support": false,
            "is_awaken": true,
            "is_lock": true,
            "need_point": 15,
            "id": 25510,
            "is_learned": false
          }
        ],
        "id": 7,
        "exp": 13207,
        "now_lv_exp": 12173
      }
    ],
    "item_magatama": [
      {
        "prc": 300,
        "effs": [
          {
            "val": 1,
            "type": 15
          },
          {
            "val": 2,
            "type": 1
          },
          {
            "val": 2,
            "type": 6
          }
        ],
        "nxt_mval": 2,
        "nxt_mval_9": 9,
        "part": 5,
        "nxt_sval_max": 2,
        "lv": 1,
        "nxt_sval": 3,
        "item_index": 2,
        "uniq": 30385715128,
        "nxt_mval_max": 9,
        "nxt_sval_9": 2,
        "is_lock": false,
        "id": 508
      }
    ],
    "smn_exp_plus": 731,
    "curr_money": 50929,
    "assist": [],
    "dvl_lv": [
      {
        "exp_pre": 16207,
        "level": 27,
        "exp_next": [
          16000,
          17655
        ],
        "id": 30478222781,
        "exp_new": 16938
      }
    ],
    "item_tag": [
      {
        "item_index": 1,
        "id": 7,
        "text": "EVENT"
      }
    ],
    "dvl": [
      {
        "agi": 49,
        "exceed_info": {
          "opened_num": 0
        },
        "hpmx": 448,
        "luk": 57,
        "devicon_power": 1036,
        "hp": 448,
        "recommend_type": 0,
        "lv": 27,
        "additional_skl": [],
        "mdef": 275,
        "limitbreak": {
          "effect": [],
          "num": 60,
          "open": []
        },
        "is_awk": false,
        "dr": 0,
        "ai_auto_type": 0,
        "mag": 32,
        "limitbreak_skl": [],
        "arc": 0,
        "wk": 4,
        "skl": [
          {
            "lv": 1,
            "id": 3028
          },
          {
            "lv": 1,
            "id": 1176
          },
          {
            "lv": 1,
            "id": 1019
          },
          {
            "lv": 1,
            "id": 103015
          },
          {
            "lv": 0,
            "id": 0
          },
          {
            "lv": 0,
            "id": 0
          },
          {
            "lv": 0,
            "id": 0
          }
        ],
        "id": 11750,
        "patk": 362,
        "exp": 16938,
        "vit": 53,
        "is_released_learn_only_skill": false,
        "st": 0,
        "pdef": 298,
        "mp": 10,
        "mgtm_effs": [],
        "lock_ex_skl": [
          true
        ],
        "is_new": true,
        "mgtms": [],
        "str": 77,
        "av": 8,
        "spt": 0,
        "uniq": 30478222781,
        "matk": 268,
        "mpmx": 10,
        "rp": 0,
        "rarity": 3,
        "contents_type": 0
      }
    ]
  },
  "is_again": false,
  "beginner_mission": {
    "is_badge": false,
    "is_display": false
  },
  "consume_ap": 4,
  "main_mission": {
    "currents": [],
    "is_display": false
  },
  "is_magatama_max": false,
  "is_advice_usable": false,
  "is_first": true,
  "first_prize": {
    "num": 500,
    "is_bonus": false,
    "id": 200,
    "type": 2
  },
  "res_code": 0,
  "client_wait": 0,
  "clear_tm": 51000,
  "best_tm": 0,
  "usr": {
    "pp": 90,
    "dp_spn": 60,
    "pp_spn": 1800,
    "pp_rec_ts": 0,
    "lv": 27,
    "dp": 100,
    "ap_itm": 0,
    "pvppt": 0,
    "rnknm": "NEWCOMER",
    "dp_rec_ts": 0,
    "dp_itm": 0,
    "usr_id": 225973463,
    "smn_id": 1,
    "mc": 50929,
    "pp_itm": 0,
    "fndmx": 18,
    "pp_boost": 0,
    "dpmx": 100,
    "mg": 366900,
    "gnd": 0,
    "exp": 60851,
    "ppmx": 5,
    "gb_exchange_ticket": 0,
    "gpmx": 2,
    "gp": 0,
    "cp": 2290,
    "rnk": "E5",
    "ap": 363,
    "nlv_exp": 63387,
    "qst_skp_ticket": 0,
    "clv_exp": 56290,
    "apmx": 36,
    "name": "Iku",
    "guild_id": 0,
    "ap_rec_ts": 0,
    "ap_spn": 180,
    "fame": 0
  },
  "is_best_record": true,
  "bonus_exp": 25,
  "is_magatama_sell": false,
  "tm": "54",
  "bonus_player_exp": 100,
  "comeback_mission": {
    "is_badge": false,
    "is_display": false
  },
  "is_card_max": false
}