{
  "item": [
    {
      "num": 41,
      "id": 5100,
      "is_use": true
    },
    {
      "num": 19,
      "id": 5200,
      "is_use": true
    },
    {
      "num": 3,
      "id": 5300,
      "is_use": true
    },
    {
      "num": 7,
      "id": 5600,
      "is_use": true
    },
    {
      "num": 5,
      "id": 5700,
      "is_use": true
    },
    {
      "num": 8,
      "id": 5800,
      "is_use": true
    },
    {
      "num": 9,
      "id": 5900,
      "is_use": true
    },
    {
      "num": 4,
      "id": 6000,
      "is_use": true
    },
    {
      "num": 1,
      "id": 6100,
      "is_use": true
    },
    {
      "num": 2,
      "id": 6200,
      "is_use": true
    },
    {
      "num": 12,
      "id": 7100,
      "is_use": false
    },
    {
      "num": 10,
      "id": 7200,
      "is_use": false
    },
    {
      "num": 12,
      "id": 7300,
      "is_use": false
    },
    {
      "num": 10,
      "id": 7400,
      "is_use": false
    },
    {
      "num": 10,
      "id": 7500,
      "is_use": false
    },
    {
      "num": 14,
      "id": 7600,
      "is_use": false
    },
    {
      "num": 6,
      "id": 7700,
      "is_use": false
    },
    {
      "num": 8,
      "id": 7800,
      "is_use": false
    }
  ],
  "beginner_mission": {
    "is_badge": false,
    "is_display": false
  },
  "main_mission": {
    "currents": [],
    "is_display": false
  },
  "tm": "10",
  "enemies": [
    {
      "skl_exp_pr": [
        0,
        0,
        0,
        0,
        0,
        0
      ],
      "agi": 278,
      "hpmx": 1084,
      "luk": 249,
      "hp": 1084,
      "atk_exp": 0,
      "lv": 85,
      "additional_skl": [],
      "mdef": 743,
      "is_rare": false,
      "limitbreak": {
        "effect": [],
        "open": []
      },
      "is_awk": false,
      "dr": 0,
      "ai_auto_type": 1,
      "mag": 222,
      "limitbreak_skl": [],
      "atk_pr": 1,
      "skl_exp": [
        0,
        0,
        0,
        0,
        0,
        0
      ],
      "decline_lower_resist": 100,
      "wk": 5,
      "pressturn": 1,
      "skl": [
        {
          "lv": 1,
          "id": 1102
        },
        {
          "lv": 1,
          "id": 103315
        },
        {
          "lv": 1,
          "id": 2007
        },
        {
          "lv": 1,
          "id": 104004
        },
        {
          "lv": 1,
          "id": 0
        },
        {
          "lv": 1,
          "id": 0
        }
      ],
      "tgt_type": 0,
      "anlz": 0,
      "id": 10840,
      "patk": 702,
      "skl_pr": [
        3,
        3,
        3,
        3,
        3,
        3
      ],
      "vit": 97,
      "st": 0,
      "pdef": 674,
      "mp": 999,
      "mgtm_effs": [],
      "atk_exp_pr": 0,
      "ai_type": 2,
      "is_dead_drama": false,
      "mgtms": [],
      "str": 84,
      "av": 2,
      "uniq": 2498,
      "matk": 992,
      "enemy_type": 0,
      "mpmx": 999,
      "rp": 0,
      "rarity": 6
    },
    {
      "agi": 167,
      "hpmx": 11340,
      "luk": 188,
      "hp": 11340,
      "res_bin": 80,
      "lv": 85,
      "additional_skl": [],
      "is_rare": false,
      "dr": 0,
      "ai_auto_type": 0,
      "limitbreak_skl": [],
      "atk_pr": 0,
      "decline_lower_resist": 100,
      "pressturn": 1,
      "skl": [
        {
          "lv": 1,
          "id": 101007
        },
        {
          "lv": 1,
          "id": 9030
        },
        {
          "lv": 1,
          "id": 1015
        },
        {
          "lv": 1,
          "id": 1164
        },
        {
          "lv": 1,
          "id": 101501
        },
        {
          "lv": 1,
          "id": 101109
        }
      ],
      "id": 11350,
      "patk": 1389,
      "vit": 188,
      "pdef": 938,
      "mp": 999,
      "mgtm_effs": [],
      "res_inf": 80,
      "ai_type": 2,
      "is_dead_drama": false,
      "str": 411,
      "av": 0,
      "uniq": 2499,
      "matk": 786,
      "enemy_type": 0,
      "mpmx": 999,
      "rp": 1,
      "rarity": 6,
      "skl_exp_pr": [
        0,
        0,
        0,
        0,
        0,
        0
      ],
      "res_cur": 80,
      "atk_exp": 0,
      "res_poi": 80,
      "mdef": 794,
      "limitbreak": {
        "effect": [],
        "open": []
      },
      "is_awk": false,
      "mag": 124,
      "skl_exp": [
        0,
        0,
        0,
        0,
        0,
        0
      ],
      "wk": 56,
      "tgt_type": 0,
      "anlz": 16,
      "skl_pr": [
        3,
        3,
        3,
        3,
        3,
        3
      ],
      "st": 0,
      "res_clo": 80,
      "atk_exp_pr": 0,
      "res_chr": 80,
      "mgtms": []
    },
    {
      "agi": 358,
      "hpmx": 8976,
      "luk": 147,
      "hp": 8976,
      "res_bin": 80,
      "lv": 85,
      "additional_skl": [],
      "is_rare": false,
      "dr": 4,
      "ai_auto_type": 2,
      "limitbreak_skl": [],
      "atk_pr": 0,
      "decline_lower_resist": 100,
      "pressturn": 1,
      "skl": [
        {
          "lv": 1,
          "id": 1020
        },
        {
          "lv": 1,
          "id": 103015
        },
        {
          "lv": 1,
          "id": 103304
        },
        {
          "lv": 1,
          "id": 1027
        },
        {
          "lv": 1,
          "id": 101501
        },
        {
          "lv": 1,
          "id": 101109
        }
      ],
      "id": 12270,
      "patk": 1275,
      "vit": 160,
      "pdef": 880,
      "mp": 999,
      "mgtm_effs": [],
      "res_inf": 80,
      "ai_type": 2,
      "is_dead_drama": false,
      "str": 357,
      "av": 0,
      "uniq": 2500,
      "matk": 834,
      "enemy_type": 0,
      "mpmx": 999,
      "rp": 0,
      "rarity": 6,
      "skl_exp_pr": [
        0,
        0,
        0,
        0,
        0,
        0
      ],
      "res_cur": 80,
      "atk_exp": 0,
      "res_poi": 80,
      "mdef": 775,
      "limitbreak": {
        "effect": [],
        "open": []
      },
      "is_awk": false,
      "mag": 147,
      "skl_exp": [
        0,
        0,
        0,
        0,
        0,
        0
      ],
      "wk": 18,
      "tgt_type": 0,
      "anlz": 19,
      "skl_pr": [
        3,
        3,
        3,
        3,
        3,
        3
      ],
      "st": 8,
      "res_clo": 80,
      "atk_exp_pr": 0,
      "res_chr": 80,
      "mgtms": []
    }
  ],
  "comeback_mission": {
    "is_badge": false,
    "is_display": false
  },
  "wave": 2,
  "wave_max": 2,
  "res_code": 0,
  "client_wait": 0
}