{
  "item": [
    {
      "num": 53,
      "id": 5100,
      "is_use": true
    },
    {
      "num": 25,
      "id": 5200,
      "is_use": true
    },
    {
      "num": 4,
      "id": 5300,
      "is_use": true
    },
    {
      "num": 10,
      "id": 5600,
      "is_use": true
    },
    {
      "num": 8,
      "id": 5700,
      "is_use": true
    },
    {
      "num": 10,
      "id": 5800,
      "is_use": true
    },
    {
      "num": 14,
      "id": 5900,
      "is_use": true
    },
    {
      "num": 4,
      "id": 6000,
      "is_use": true
    },
    {
      "num": 1,
      "id": 6100,
      "is_use": true
    },
    {
      "num": 2,
      "id": 6200,
      "is_use": true
    },
    {
      "num": 1,
      "id": 6300,
      "is_use": true
    },
    {
      "num": 13,
      "id": 7100,
      "is_use": false
    },
    {
      "num": 11,
      "id": 7200,
      "is_use": false
    },
    {
      "num": 17,
      "id": 7300,
      "is_use": false
    },
    {
      "num": 15,
      "id": 7400,
      "is_use": false
    },
    {
      "num": 12,
      "id": 7500,
      "is_use": false
    },
    {
      "num": 16,
      "id": 7600,
      "is_use": false
    },
    {
      "num": 9,
      "id": 7700,
      "is_use": false
    },
    {
      "num": 9,
      "id": 7800,
      "is_use": false
    }
  ],
  "beginner_mission": {
    "is_badge": false,
    "is_display": false
  },
  "main_mission": {
    "currents": [],
    "is_display": false
  },
  "enemies": [
    {
      "skl_exp_pr": [
        0,
        0,
        0,
        0,
        0,
        0
      ],
      "agi": 57,
      "hpmx": 565,
      "luk": 70,
      "hp": 565,
      "atk_exp": 0,
      "lv": 32,
      "additional_skl": [],
      "mdef": 348,
      "is_rare": false,
      "limitbreak": {
        "effect": [],
        "open": []
      },
      "is_awk": true,
      "dr": 0,
      "ai_auto_type": 1,
      "mag": 85,
      "limitbreak_skl": [],
      "atk_pr": 1,
      "skl_exp": [
        0,
        0,
        0,
        0,
        0,
        0
      ],
      "decline_lower_resist": 100,
      "wk": 2,
      "pressturn": 1,
      "skl": [
        {
          "lv": 1,
          "id": 2010
        },
        {
          "lv": 1,
          "id": 1110
        },
        {
          "lv": 1,
          "id": 2002
        },
        {
          "lv": 1,
          "id": 0
        },
        {
          "lv": 1,
          "id": 0
        },
        {
          "lv": 1,
          "id": 0
        }
      ],
      "tgt_type": 0,
      "anlz": 0,
      "id": 12430,
      "patk": 319,
      "skl_pr": [
        0,
        3,
        3,
        3,
        3,
        3
      ],
      "vit": 70,
      "st": 4,
      "pdef": 327,
      "mp": 999,
      "mgtm_effs": [],
      "atk_exp_pr": 0,
      "ai_type": 2,
      "is_dead_drama": false,
      "mgtms": [],
      "str": 43,
      "av": 0,
      "uniq": 150,
      "matk": 407,
      "enemy_type": 0,
      "mpmx": 999,
      "rp": 0,
      "rarity": 3
    },
    {
      "skl_exp_pr": [
        0,
        0,
        0,
        0,
        0,
        0
      ],
      "agi": 57,
      "hpmx": 565,
      "luk": 70,
      "hp": 565,
      "atk_exp": 0,
      "lv": 32,
      "additional_skl": [],
      "mdef": 348,
      "is_rare": false,
      "limitbreak": {
        "effect": [],
        "open": []
      },
      "is_awk": true,
      "dr": 0,
      "ai_auto_type": 1,
      "mag": 85,
      "limitbreak_skl": [],
      "atk_pr": 1,
      "skl_exp": [
        0,
        0,
        0,
        0,
        0,
        0
      ],
      "decline_lower_resist": 100,
      "wk": 2,
      "pressturn": 1,
      "skl": [
        {
          "lv": 1,
          "id": 2010
        },
        {
          "lv": 1,
          "id": 1110
        },
        {
          "lv": 1,
          "id": 2002
        },
        {
          "lv": 1,
          "id": 0
        },
        {
          "lv": 1,
          "id": 0
        },
        {
          "lv": 1,
          "id": 0
        }
      ],
      "tgt_type": 0,
      "anlz": 0,
      "id": 12430,
      "patk": 319,
      "skl_pr": [
        0,
        3,
        3,
        3,
        3,
        3
      ],
      "vit": 70,
      "st": 4,
      "pdef": 327,
      "mp": 999,
      "mgtm_effs": [],
      "atk_exp_pr": 0,
      "ai_type": 2,
      "is_dead_drama": false,
      "mgtms": [],
      "str": 43,
      "av": 0,
      "uniq": 151,
      "matk": 407,
      "enemy_type": 0,
      "mpmx": 999,
      "rp": 0,
      "rarity": 3
    },
    {
      "skl_exp_pr": [
        0,
        0,
        0,
        0,
        0,
        0
      ],
      "agi": 74,
      "hpmx": 612,
      "luk": 70,
      "hp": 612,
      "atk_exp": 0,
      "lv": 32,
      "additional_skl": [],
      "mdef": 341,
      "is_rare": false,
      "limitbreak": {
        "effect": [],
        "open": []
      },
      "is_awk": true,
      "dr": 0,
      "ai_auto_type": 0,
      "mag": 48,
      "limitbreak_skl": [],
      "atk_pr": 1,
      "skl_exp": [
        0,
        0,
        0,
        0,
        0,
        0
      ],
      "decline_lower_resist": 100,
      "wk": 8,
      "pressturn": 1,
      "skl": [
        {
          "lv": 1,
          "id": 1128
        },
        {
          "lv": 1,
          "id": 1001
        },
        {
          "lv": 1,
          "id": 1160
        },
        {
          "lv": 1,
          "id": 0
        },
        {
          "lv": 1,
          "id": 0
        },
        {
          "lv": 1,
          "id": 0
        }
      ],
      "tgt_type": 0,
      "anlz": 0,
      "id": 11920,
      "patk": 346,
      "skl_pr": [
        3,
        3,
        3,
        3,
        3,
        3
      ],
      "vit": 80,
      "st": 16,
      "pdef": 345,
      "mp": 999,
      "mgtm_effs": [],
      "atk_exp_pr": 0,
      "ai_type": 2,
      "is_dead_drama": false,
      "mgtms": [],
      "str": 56,
      "av": 0,
      "uniq": 152,
      "matk": 330,
      "enemy_type": 0,
      "mpmx": 999,
      "rp": 0,
      "rarity": 3
    }
  ],
  "wave": 3,
  "res_code": 0,
  "client_wait": 0,
  "tm": "97",
  "talk": {
    "talk_start_type": 1,
    "talk_tgt": 150
  },
  "comeback_mission": {
    "is_badge": false,
    "is_display": false
  },
  "wave_max": 3
}